{
  "incumbent_ids": [],
  "rejected_config_ids": [],
  "incumbents_changed": 0,
  "trajectory": [],
  "state": {
    "tracker": {
      "0,0": [
        [
          0,
          [
            {
              "batch_size": 77,
              "budget_type": "img_size",
              "cv_count": 2,
              "dataset": "deepweedsx_balanced",
              "datasetpath": "/home/shady/Projects/automl_final/data",
              "device": "cpu",
              "dropout_rate": 0.2,
              "global_avg_pooling": false,
              "kernel_size": 3,
              "learning_rate_init": 0.00018662266976517952,
              "n_channels_conv_0": 107,
              "n_channels_fc_0": 122,
              "n_conv_layers": 3,
              "n_fc_layers": 2,
              "use_BN": true,
              "n_channels_conv_1": 17,
              "n_channels_conv_2": 138,
              "n_channels_fc_1": 63
            },
            {
              "batch_size": 96,
              "budget_type": "img_size",
              "cv_count": 2,
              "dataset": "deepweedsx_balanced",
              "datasetpath": "/home/shady/Projects/automl_final/data",
              "device": "cpu",
              "dropout_rate": 0.2,
              "global_avg_pooling": false,
              "kernel_size": 3,
              "learning_rate_init": 0.0008663279761354553,
              "n_channels_conv_0": 379,
              "n_channels_fc_0": 54,
              "n_conv_layers": 2,
              "n_fc_layers": 3,
              "use_BN": true,
              "n_channels_conv_1": 285,
              "n_channels_fc_1": 48,
              "n_channels_fc_2": 47
            },
            {
              "batch_size": 28,
              "budget_type": "img_size",
              "cv_count": 2,
              "dataset": "deepweedsx_balanced",
              "datasetpath": "/home/shady/Projects/automl_final/data",
              "device": "cpu",
              "dropout_rate": 0.2,
              "global_avg_pooling": false,
              "kernel_size": 3,
              "learning_rate_init": 2.6919058249260695e-05,
              "n_channels_conv_0": 439,
              "n_channels_fc_0": 66,
              "n_conv_layers": 2,
              "n_fc_layers": 1,
              "use_BN": false,
              "n_channels_conv_1": 76
            },
            {
              "batch_size": 84,
              "budget_type": "img_size",
              "cv_count": 2,
              "dataset": "deepweedsx_balanced",
              "datasetpath": "/home/shady/Projects/automl_final/data",
              "device": "cpu",
              "dropout_rate": 0.2,
              "global_avg_pooling": false,
              "kernel_size": 3,
              "learning_rate_init": 0.006780227021579835,
              "n_channels_conv_0": 211,
              "n_channels_fc_0": 52,
              "n_conv_layers": 2,
              "n_fc_layers": 3,
              "use_BN": true,
              "n_channels_conv_1": 160,
              "n_channels_fc_1": 21,
              "n_channels_fc_2": 19
            },
            {
              "batch_size": 50,
              "budget_type": "img_size",
              "cv_count": 2,
              "dataset": "deepweedsx_balanced",
              "datasetpath": "/home/shady/Projects/automl_final/data",
              "device": "cpu",
              "dropout_rate": 0.2,
              "global_avg_pooling": true,
              "kernel_size": 3,
              "learning_rate_init": 0.0005135589606500231,
              "n_channels_conv_0": 107,
              "n_channels_fc_0": 126,
              "n_conv_layers": 1,
              "n_fc_layers": 1,
              "use_BN": true
            },
            {
              "batch_size": 33,
              "budget_type": "img_size",
              "cv_count": 2,
              "dataset": "deepweedsx_balanced",
              "datasetpath": "/home/shady/Projects/automl_final/data",
              "device": "cpu",
              "dropout_rate": 0.2,
              "global_avg_pooling": true,
              "kernel_size": 3,
              "learning_rate_init": 0.0009310837957239842,
              "n_channels_conv_0": 46,
              "n_channels_fc_0": 42,
              "n_conv_layers": 2,
              "n_fc_layers": 3,
              "use_BN": true,
              "n_channels_conv_1": 291,
              "n_channels_fc_1": 62,
              "n_channels_fc_2": 30
            },
            {
              "batch_size": 126,
              "budget_type": "img_size",
              "cv_count": 2,
              "dataset": "deepweedsx_balanced",
              "datasetpath": "/home/shady/Projects/automl_final/data",
              "device": "cpu",
              "dropout_rate": 0.2,
              "global_avg_pooling": false,
              "kernel_size": 3,
              "learning_rate_init": 0.00165116600355318,
              "n_channels_conv_0": 35,
              "n_channels_fc_0": 47,
              "n_conv_layers": 1,
              "n_fc_layers": 1,
              "use_BN": true
            },
            {
              "batch_size": 79,
              "budget_type": "img_size",
              "cv_count": 2,
              "dataset": "deepweedsx_balanced",
              "datasetpath": "/home/shady/Projects/automl_final/data",
              "device": "cpu",
              "dropout_rate": 0.2,
              "global_avg_pooling": true,
              "kernel_size": 3,
              "learning_rate_init": 0.00037131642495346224,
              "n_channels_conv_0": 41,
              "n_channels_fc_0": 71,
              "n_conv_layers": 3,
              "n_fc_layers": 1,
              "use_BN": false,
              "n_channels_conv_1": 25,
              "n_channels_conv_2": 116
            }
          ]
        ]
      ],
      "1,0": [
        [
          0,
          [
            {
              "batch_size": 81,
              "budget_type": "img_size",
              "cv_count": 2,
              "dataset": "deepweedsx_balanced",
              "datasetpath": "/home/shady/Projects/automl_final/data",
              "device": "cpu",
              "dropout_rate": 0.2,
              "global_avg_pooling": true,
              "kernel_size": 3,
              "learning_rate_init": 0.0030677508679378784,
              "n_channels_conv_0": 32,
              "n_channels_fc_0": 82,
              "n_conv_layers": 1,
              "n_fc_layers": 3,
              "use_BN": false,
              "n_channels_fc_1": 36,
              "n_channels_fc_2": 35
            },
            {
              "batch_size": 40,
              "budget_type": "img_size",
              "cv_count": 2,
              "dataset": "deepweedsx_balanced",
              "datasetpath": "/home/shady/Projects/automl_final/data",
              "device": "cpu",
              "dropout_rate": 0.2,
              "global_avg_pooling": false,
              "kernel_size": 3,
              "learning_rate_init": 0.00021947049130435368,
              "n_channels_conv_0": 334,
              "n_channels_fc_0": 84,
              "n_conv_layers": 1,
              "n_fc_layers": 3,
              "use_BN": true,
              "n_channels_fc_1": 54,
              "n_channels_fc_2": 42
            },
            {
              "batch_size": 97,
              "budget_type": "img_size",
              "cv_count": 2,
              "dataset": "deepweedsx_balanced",
              "datasetpath": "/home/shady/Projects/automl_final/data",
              "device": "cpu",
              "dropout_rate": 0.2,
              "global_avg_pooling": false,
              "kernel_size": 3,
              "learning_rate_init": 0.007383306613811968,
              "n_channels_conv_0": 190,
              "n_channels_fc_0": 57,
              "n_conv_layers": 2,
              "n_fc_layers": 1,
              "use_BN": true,
              "n_channels_conv_1": 156
            },
            {
              "batch_size": 30,
              "budget_type": "img_size",
              "cv_count": 2,
              "dataset": "deepweedsx_balanced",
              "datasetpath": "/home/shady/Projects/automl_final/data",
              "device": "cpu",
              "dropout_rate": 0.2,
              "global_avg_pooling": true,
              "kernel_size": 3,
              "learning_rate_init": 0.0005127370874628437,
              "n_channels_conv_0": 164,
              "n_channels_fc_0": 71,
              "n_conv_layers": 2,
              "n_fc_layers": 2,
              "use_BN": true,
              "n_channels_conv_1": 357,
              "n_channels_fc_1": 29
            },
            {
              "batch_size": 106,
              "budget_type": "img_size",
              "cv_count": 2,
              "dataset": "deepweedsx_balanced",
              "datasetpath": "/home/shady/Projects/automl_final/data",
              "device": "cpu",
              "dropout_rate": 0.2,
              "global_avg_pooling": false,
              "kernel_size": 3,
              "learning_rate_init": 1.9983919055737704e-05,
              "n_channels_conv_0": 409,
              "n_channels_fc_0": 86,
              "n_conv_layers": 3,
              "n_fc_layers": 1,
              "use_BN": false,
              "n_channels_conv_1": 27,
              "n_channels_conv_2": 87
            },
            {
              "batch_size": 107,
              "budget_type": "img_size",
              "cv_count": 2,
              "dataset": "deepweedsx_balanced",
              "datasetpath": "/home/shady/Projects/automl_final/data",
              "device": "cpu",
              "dropout_rate": 0.2,
              "global_avg_pooling": false,
              "kernel_size": 3,
              "learning_rate_init": 0.00016655201514737645,
              "n_channels_conv_0": 38,
              "n_channels_fc_0": 84,
              "n_conv_layers": 2,
              "n_fc_layers": 3,
              "use_BN": false,
              "n_channels_conv_1": 470,
              "n_channels_fc_1": 16,
              "n_channels_fc_2": 26
            }
          ]
        ]
      ],
      "2,0": [
        [
          0,
          [
            {
              "batch_size": 98,
              "budget_type": "img_size",
              "cv_count": 2,
              "dataset": "deepweedsx_balanced",
              "datasetpath": "/home/shady/Projects/automl_final/data",
              "device": "cpu",
              "dropout_rate": 0.2,
              "global_avg_pooling": true,
              "kernel_size": 3,
              "learning_rate_init": 0.000365687250050888,
              "n_channels_conv_0": 37,
              "n_channels_fc_0": 42,
              "n_conv_layers": 1,
              "n_fc_layers": 3,
              "use_BN": true,
              "n_channels_fc_1": 42,
              "n_channels_fc_2": 16
            },
            {
              "batch_size": 33,
              "budget_type": "img_size",
              "cv_count": 2,
              "dataset": "deepweedsx_balanced",
              "datasetpath": "/home/shady/Projects/automl_final/data",
              "device": "cpu",
              "dropout_rate": 0.2,
              "global_avg_pooling": false,
              "kernel_size": 3,
              "learning_rate_init": 0.0005391204002783814,
              "n_channels_conv_0": 61,
              "n_channels_fc_0": 117,
              "n_conv_layers": 2,
              "n_fc_layers": 2,
              "use_BN": false,
              "n_channels_conv_1": 199,
              "n_channels_fc_1": 27
            },
            {
              "batch_size": 36,
              "budget_type": "img_size",
              "cv_count": 2,
              "dataset": "deepweedsx_balanced",
              "datasetpath": "/home/shady/Projects/automl_final/data",
              "device": "cpu",
              "dropout_rate": 0.2,
              "global_avg_pooling": false,
              "kernel_size": 3,
              "learning_rate_init": 0.0016544451942874174,
              "n_channels_conv_0": 124,
              "n_channels_fc_0": 43,
              "n_conv_layers": 1,
              "n_fc_layers": 1,
              "use_BN": true
            },
            {
              "batch_size": 17,
              "budget_type": "img_size",
              "cv_count": 2,
              "dataset": "deepweedsx_balanced",
              "datasetpath": "/home/shady/Projects/automl_final/data",
              "device": "cpu",
              "dropout_rate": 0.2,
              "global_avg_pooling": true,
              "kernel_size": 3,
              "learning_rate_init": 0.001091888571809732,
              "n_channels_conv_0": 112,
              "n_channels_fc_0": 67,
              "n_conv_layers": 3,
              "n_fc_layers": 3,
              "use_BN": true,
              "n_channels_conv_1": 158,
              "n_channels_conv_2": 32,
              "n_channels_fc_1": 16,
              "n_channels_fc_2": 46
            }
          ]
        ]
      ]
    },
    "next_bracket": 3
  }
}